[
{
"comment":"OneMinuteFocusExposure",
"filter":"g",
"seqtot":13,
"seqnum":1,
"seqid":"2023A",
"expType":"object",
"object":"1minexp_000",
"proposer":"Leauthaud",
"program":"Merian",
"RA":220.1188856978,
"propid":"2020B-0288",
"dec":2.827650365,
"expTime":60.0,
"count":1,
"wait":"False"
},
{
"comment":"--",
"filter":"g",
"seqtot":13,
"seqnum":2,
"seqid":"2023A",
"expType":"object",
"object":"NSA15235_J144028.53+024939.54_g",
"proposer":"Leauthaud",
"program":"Merian",
"RA":220.1188856978,
"propid":"2020B-0288",
"dec":2.827650365,
"expTime":300.0,
"count":1,
"wait":"False"
},
{
"comment":"--",
"filter":"g",
"seqtot":13,
"seqnum":3,
"seqid":"2023A",
"expType":"object",
"object":"NSA15235_J144047.45+025452.69_g",
"proposer":"Leauthaud",
"program":"Merian",
"RA":220.1977428014,
"propid":"2020B-0288",
"dec":2.9146367406,
"expTime":300.0,
"count":1,
"wait":"False"
},
{
"comment":"--",
"filter":"g",
"seqtot":13,
"seqnum":4,
"seqid":"2023A",
"expType":"object",
"object":"NSA15235_J144048.83+025202.28_g",
"proposer":"Leauthaud",
"program":"Merian",
"RA":220.2034875477,
"propid":"2020B-0288",
"dec":2.8673012144,
"expTime":300.0,
"count":1,
"wait":"False"
},
{
"comment":"--",
"filter":"g",
"seqtot":13,
"seqnum":5,
"seqid":"2023A",
"expType":"object",
"object":"NSA15235_J144048.69+024949.33_g",
"proposer":"Leauthaud",
"program":"Merian",
"RA":220.20288345,
"propid":"2020B-0288",
"dec":2.830371845,
"expTime":300.0,
"count":1,
"wait":"False"
},
{
"comment":"--",
"filter":"g",
"seqtot":13,
"seqnum":6,
"seqid":"2023A",
"expType":"object",
"object":"NSA15235_J144004.26+024700.80_g",
"proposer":"Leauthaud",
"program":"Merian",
"RA":220.0177533369,
"propid":"2020B-0288",
"dec":2.7835581737,
"expTime":300.0,
"count":1,
"wait":"False"
},
{
"comment":"--",
"filter":"g",
"seqtot":13,
"seqnum":7,
"seqid":"2023A",
"expType":"object",
"object":"NSA15235_J144003.35+025553.98_g",
"proposer":"Leauthaud",
"program":"Merian",
"RA":220.0139617019,
"propid":"2020B-0288",
"dec":2.9316623619,
"expTime":300.0,
"count":1,
"wait":"False"
},
{
"comment":"--",
"filter":"g",
"seqtot":13,
"seqnum":8,
"seqid":"2023A",
"expType":"object",
"object":"NSA15235_J144028.24+025230.69_g",
"proposer":"Leauthaud",
"program":"Merian",
"RA":220.1176726263,
"propid":"2020B-0288",
"dec":2.8751935708,
"expTime":300.0,
"count":1,
"wait":"False"
},
{
"comment":"--",
"filter":"g",
"seqtot":13,
"seqnum":9,
"seqid":"2023A",
"expType":"object",
"object":"NSA15235_J144027.24+025041.08_g",
"proposer":"Leauthaud",
"program":"Merian",
"RA":220.113513961,
"propid":"2020B-0288",
"dec":2.8447445355,
"expTime":300.0,
"count":1,
"wait":"False"
},
{
"comment":"--",
"filter":"g",
"seqtot":13,
"seqnum":10,
"seqid":"2023A",
"expType":"object",
"object":"NSA15235_J144050.07+024344.22_g",
"proposer":"Leauthaud",
"program":"Merian",
"RA":220.2086516067,
"propid":"2020B-0288",
"dec":2.7289501286,
"expTime":300.0,
"count":1,
"wait":"False"
},
{
"comment":"--",
"filter":"g",
"seqtot":13,
"seqnum":11,
"seqid":"2023A",
"expType":"object",
"object":"NSA15235_J144011.45+024827.49_g",
"proposer":"Leauthaud",
"program":"Merian",
"RA":220.0477476706,
"propid":"2020B-0288",
"dec":2.8076367191,
"expTime":300.0,
"count":1,
"wait":"False"
},
{
"comment":"--",
"filter":"g",
"seqtot":13,
"seqnum":12,
"seqid":"2023A",
"expType":"object",
"object":"NSA15235_J144048.05+025030.77_g",
"proposer":"Leauthaud",
"program":"Merian",
"RA":220.2002168095,
"propid":"2020B-0288",
"dec":2.8418817431,
"expTime":300.0,
"count":1,
"wait":"False"
},
{
"comment":"--",
"filter":"g",
"seqtot":13,
"seqnum":13,
"seqid":"2023A",
"expType":"object",
"object":"NSA15235_J144027.44+024748.17_g",
"proposer":"Leauthaud",
"program":"Merian",
"RA":220.1143342613,
"propid":"2020B-0288",
"dec":2.79671397,
"expTime":300.0,
"count":1,
"wait":"False"
}
]