[
{
"comment":"OneMinuteFocusExposure",
"filter":"g",
"seqtot":13,
"seqnum":1,
"seqid":"2022B",
"expType":"object",
"object":"1minexp_000",
"proposer":"Leauthaud",
"program":"Merian",
"RA":344.6030656,
"propid":"2020B-0288",
"dec":-31.2366291,
"expTime":60.0,
"count":1,
"wait":"False"
},
{
"comment":"--",
"filter":"g",
"seqtot":13,
"seqnum":2,
"seqid":"2022B",
"expType":"object",
"object":"GAMA5265117_J225824.73-311411.86_g",
"proposer":"Leauthaud",
"program":"Merian",
"RA":344.6030656,
"propid":"2020B-0288",
"dec":-31.2366291,
"expTime":300.0,
"count":1,
"wait":"False"
},
{
"comment":"--",
"filter":"g",
"seqtot":13,
"seqnum":3,
"seqid":"2022B",
"expType":"object",
"object":"GAMA5265117_J225843.09-311909.67_g",
"proposer":"Leauthaud",
"program":"Merian",
"RA":344.6795817354,
"propid":"2020B-0288",
"dec":-31.3193547668,
"expTime":300.0,
"count":1,
"wait":"False"
},
{
"comment":"--",
"filter":"g",
"seqtot":13,
"seqnum":4,
"seqid":"2022B",
"expType":"object",
"object":"GAMA5265117_J225835.91-311328.86_g",
"proposer":"Leauthaud",
"program":"Merian",
"RA":344.6496571134,
"propid":"2020B-0288",
"dec":-31.2246842585,
"expTime":300.0,
"count":1,
"wait":"False"
},
{
"comment":"--",
"filter":"g",
"seqtot":13,
"seqnum":5,
"seqid":"2022B",
"expType":"object",
"object":"GAMA5265117_J225826.24-311358.73_g",
"proposer":"Leauthaud",
"program":"Merian",
"RA":344.6093376831,
"propid":"2020B-0288",
"dec":-31.232982245,
"expTime":300.0,
"count":1,
"wait":"False"
},
{
"comment":"--",
"filter":"g",
"seqtot":13,
"seqnum":6,
"seqid":"2022B",
"expType":"object",
"object":"GAMA5265117_J225801.93-310928.63_g",
"proposer":"Leauthaud",
"program":"Merian",
"RA":344.5080829083,
"propid":"2020B-0288",
"dec":-31.1579539348,
"expTime":300.0,
"count":1,
"wait":"False"
},
{
"comment":"--",
"filter":"g",
"seqtot":13,
"seqnum":7,
"seqid":"2022B",
"expType":"object",
"object":"GAMA5265117_J225817.18-311742.23_g",
"proposer":"Leauthaud",
"program":"Merian",
"RA":344.571592749,
"propid":"2020B-0288",
"dec":-31.2950652742,
"expTime":300.0,
"count":1,
"wait":"False"
},
{
"comment":"--",
"filter":"g",
"seqtot":13,
"seqnum":8,
"seqid":"2022B",
"expType":"object",
"object":"GAMA5265117_J225831.50-311735.20_g",
"proposer":"Leauthaud",
"program":"Merian",
"RA":344.6312819032,
"propid":"2020B-0288",
"dec":-31.2931113549,
"expTime":300.0,
"count":1,
"wait":"False"
},
{
"comment":"--",
"filter":"g",
"seqtot":13,
"seqnum":9,
"seqid":"2022B",
"expType":"object",
"object":"GAMA5265117_J225836.17-310902.86_g",
"proposer":"Leauthaud",
"program":"Merian",
"RA":344.6507125407,
"propid":"2020B-0288",
"dec":-31.1507952918,
"expTime":300.0,
"count":1,
"wait":"False"
},
{
"comment":"--",
"filter":"g",
"seqtot":13,
"seqnum":10,
"seqid":"2022B",
"expType":"object",
"object":"GAMA5265117_J225847.37-310935.61_g",
"proposer":"Leauthaud",
"program":"Merian",
"RA":344.6973909503,
"propid":"2020B-0288",
"dec":-31.1598931192,
"expTime":300.0,
"count":1,
"wait":"False"
},
{
"comment":"--",
"filter":"g",
"seqtot":13,
"seqnum":11,
"seqid":"2022B",
"expType":"object",
"object":"GAMA5265117_J225836.57-311242.09_g",
"proposer":"Leauthaud",
"program":"Merian",
"RA":344.6523894842,
"propid":"2020B-0288",
"dec":-31.2116929182,
"expTime":300.0,
"count":1,
"wait":"False"
},
{
"comment":"--",
"filter":"g",
"seqtot":13,
"seqnum":12,
"seqid":"2022B",
"expType":"object",
"object":"GAMA5265117_J225822.53-312029.18_g",
"proposer":"Leauthaud",
"program":"Merian",
"RA":344.5938993023,
"propid":"2020B-0288",
"dec":-31.3414399922,
"expTime":300.0,
"count":1,
"wait":"False"
},
{
"comment":"--",
"filter":"g",
"seqtot":13,
"seqnum":13,
"seqid":"2022B",
"expType":"object",
"object":"GAMA5265117_J225819.71-311400.24_g",
"proposer":"Leauthaud",
"program":"Merian",
"RA":344.5821571833,
"propid":"2020B-0288",
"dec":-31.233401951,
"expTime":300.0,
"count":1,
"wait":"False"
}
]