[
{
"comment":"OneMinuteFocusExposure",
"filter":"i",
"seqtot":100,
"seqnum":1,
"seqid":"2022B",
"expType":"object",
"object":"1minexp_000",
"proposer":"Leauthaud",
"program":"Merian",
"RA":18.418,
"propid":"2020B-0288",
"dec":-59.72622222,
"expTime":60.0,
"count":1,
"wait":"False"
},
{
"comment":"--",
"filter":"i",
"seqtot":100,
"seqnum":2,
"seqid":"2022B",
"expType":"object",
"object":"TIC206544316_offset_J011340.32-594334.39_i",
"proposer":"Leauthaud",
"program":"Merian",
"RA":18.418,
"propid":"2020B-0288",
"dec":-59.72622222,
"expTime":3.0,
"count":1,
"wait":"False"
},
{
"comment":"--",
"filter":"i",
"seqtot":100,
"seqnum":3,
"seqid":"2022B",
"expType":"object",
"object":"TIC206544316_offset_J011333.55-594631.32_i",
"proposer":"Leauthaud",
"program":"Merian",
"RA":18.3898216374,
"propid":"2020B-0288",
"dec":-59.7753679911,
"expTime":3.0,
"count":1,
"wait":"False"
},
{
"comment":"--",
"filter":"i",
"seqtot":100,
"seqnum":4,
"seqid":"2022B",
"expType":"object",
"object":"TIC206544316_offset_J011331.87-594623.63_i",
"proposer":"Leauthaud",
"program":"Merian",
"RA":18.3828072427,
"propid":"2020B-0288",
"dec":-59.7732310837,
"expTime":3.0,
"count":1,
"wait":"False"
},
{
"comment":"--",
"filter":"i",
"seqtot":100,
"seqnum":5,
"seqid":"2022B",
"expType":"object",
"object":"TIC206544316_offset_J011322.55-593732.71_i",
"proposer":"Leauthaud",
"program":"Merian",
"RA":18.3439952562,
"propid":"2020B-0288",
"dec":-59.6257533218,
"expTime":3.0,
"count":1,
"wait":"False"
},
{
"comment":"--",
"filter":"i",
"seqtot":100,
"seqnum":6,
"seqid":"2022B",
"expType":"object",
"object":"TIC206544316_offset_J011323.99-594544.85_i",
"proposer":"Leauthaud",
"program":"Merian",
"RA":18.3499796747,
"propid":"2020B-0288",
"dec":-59.7624589536,
"expTime":3.0,
"count":1,
"wait":"False"
},
{
"comment":"--",
"filter":"i",
"seqtot":100,
"seqnum":7,
"seqid":"2022B",
"expType":"object",
"object":"TIC206544316_offset_J011343.68-593815.02_i",
"proposer":"Leauthaud",
"program":"Merian",
"RA":18.4320150329,
"propid":"2020B-0288",
"dec":-59.6375061374,
"expTime":3.0,
"count":1,
"wait":"False"
},
{
"comment":"--",
"filter":"i",
"seqtot":100,
"seqnum":8,
"seqid":"2022B",
"expType":"object",
"object":"TIC206544316_offset_J011324.21-594746.75_i",
"proposer":"Leauthaud",
"program":"Merian",
"RA":18.3509124766,
"propid":"2020B-0288",
"dec":-59.7963207643,
"expTime":3.0,
"count":1,
"wait":"False"
},
{
"comment":"--",
"filter":"i",
"seqtot":100,
"seqnum":9,
"seqid":"2022B",
"expType":"object",
"object":"TIC206544316_offset_J011329.51-593902.67_i",
"proposer":"Leauthaud",
"program":"Merian",
"RA":18.3729587333,
"propid":"2020B-0288",
"dec":-59.6507433139,
"expTime":3.0,
"count":1,
"wait":"False"
},
{
"comment":"--",
"filter":"i",
"seqtot":100,
"seqnum":10,
"seqid":"2022B",
"expType":"object",
"object":"TIC206544316_offset_J011355.88-593729.70_i",
"proposer":"Leauthaud",
"program":"Merian",
"RA":18.482845327,
"propid":"2020B-0288",
"dec":-59.6249174458,
"expTime":3.0,
"count":1,
"wait":"False"
},
{
"comment":"--",
"filter":"i",
"seqtot":100,
"seqnum":11,
"seqid":"2022B",
"expType":"object",
"object":"TIC206544316_offset_J011334.18-594206.30_i",
"proposer":"Leauthaud",
"program":"Merian",
"RA":18.3924309071,
"propid":"2020B-0288",
"dec":-59.7017517792,
"expTime":3.0,
"count":1,
"wait":"False"
},
{
"comment":"--",
"filter":"i",
"seqtot":100,
"seqnum":12,
"seqid":"2022B",
"expType":"object",
"object":"TIC206544316_offset_J011327.26-594434.35_i",
"proposer":"Leauthaud",
"program":"Merian",
"RA":18.3636000062,
"propid":"2020B-0288",
"dec":-59.7428750942,
"expTime":3.0,
"count":1,
"wait":"False"
},
{
"comment":"--",
"filter":"i",
"seqtot":100,
"seqnum":13,
"seqid":"2022B",
"expType":"object",
"object":"TIC206544316_offset_J011353.93-594739.88_i",
"proposer":"Leauthaud",
"program":"Merian",
"RA":18.4747490499,
"propid":"2020B-0288",
"dec":-59.7944136326,
"expTime":3.0,
"count":1,
"wait":"False"
},
{
"comment":"--",
"filter":"i",
"seqtot":100,
"seqnum":14,
"seqid":"2022B",
"expType":"object",
"object":"TIC206544316_offset_J011353.98-594620.45_i",
"proposer":"Leauthaud",
"program":"Merian",
"RA":18.4749282403,
"propid":"2020B-0288",
"dec":-59.7723474198,
"expTime":3.0,
"count":1,
"wait":"False"
},
{
"comment":"--",
"filter":"i",
"seqtot":100,
"seqnum":15,
"seqid":"2022B",
"expType":"object",
"object":"TIC206544316_offset_J011331.09-594051.88_i",
"proposer":"Leauthaud",
"program":"Merian",
"RA":18.3795722961,
"propid":"2020B-0288",
"dec":-59.6810786104,
"expTime":3.0,
"count":1,
"wait":"False"
},
{
"comment":"--",
"filter":"i",
"seqtot":100,
"seqnum":16,
"seqid":"2022B",
"expType":"object",
"object":"TIC206544316_offset_J011346.94-594458.15_i",
"proposer":"Leauthaud",
"program":"Merian",
"RA":18.4456241777,
"propid":"2020B-0288",
"dec":-59.7494883749,
"expTime":3.0,
"count":1,
"wait":"False"
},
{
"comment":"--",
"filter":"i",
"seqtot":100,
"seqnum":17,
"seqid":"2022B",
"expType":"object",
"object":"TIC206544316_offset_J011342.60-593800.98_i",
"proposer":"Leauthaud",
"program":"Merian",
"RA":18.427528223,
"propid":"2020B-0288",
"dec":-59.6336062385,
"expTime":3.0,
"count":1,
"wait":"False"
},
{
"comment":"--",
"filter":"i",
"seqtot":100,
"seqnum":18,
"seqid":"2022B",
"expType":"object",
"object":"TIC206544316_offset_J011329.15-594331.01_i",
"proposer":"Leauthaud",
"program":"Merian",
"RA":18.3714802485,
"propid":"2020B-0288",
"dec":-59.7252815048,
"expTime":3.0,
"count":1,
"wait":"False"
},
{
"comment":"--",
"filter":"i",
"seqtot":100,
"seqnum":19,
"seqid":"2022B",
"expType":"object",
"object":"TIC206544316_offset_J011402.50-594058.26_i",
"proposer":"Leauthaud",
"program":"Merian",
"RA":18.5104209423,
"propid":"2020B-0288",
"dec":-59.6828516941,
"expTime":3.0,
"count":1,
"wait":"False"
},
{
"comment":"--",
"filter":"i",
"seqtot":100,
"seqnum":20,
"seqid":"2022B",
"expType":"object",
"object":"TIC206544316_offset_J011323.44-594314.40_i",
"proposer":"Leauthaud",
"program":"Merian",
"RA":18.3477037124,
"propid":"2020B-0288",
"dec":-59.7206677917,
"expTime":3.0,
"count":1,
"wait":"False"
},
{
"comment":"--",
"filter":"i",
"seqtot":100,
"seqnum":21,
"seqid":"2022B",
"expType":"object",
"object":"TIC206544316_offset_J011322.35-594124.14_i",
"proposer":"Leauthaud",
"program":"Merian",
"RA":18.3431628951,
"propid":"2020B-0288",
"dec":-59.6900401782,
"expTime":3.0,
"count":1,
"wait":"False"
},
{
"comment":"--",
"filter":"i",
"seqtot":100,
"seqnum":22,
"seqid":"2022B",
"expType":"object",
"object":"TIC206544316_offset_J011358.99-594241.00_i",
"proposer":"Leauthaud",
"program":"Merian",
"RA":18.4958059086,
"propid":"2020B-0288",
"dec":-59.7113912487,
"expTime":3.0,
"count":1,
"wait":"False"
},
{
"comment":"--",
"filter":"i",
"seqtot":100,
"seqnum":23,
"seqid":"2022B",
"expType":"object",
"object":"TIC206544316_offset_J011329.90-594701.33_i",
"proposer":"Leauthaud",
"program":"Merian",
"RA":18.3746018792,
"propid":"2020B-0288",
"dec":-59.7837049298,
"expTime":3.0,
"count":1,
"wait":"False"
},
{
"comment":"--",
"filter":"i",
"seqtot":100,
"seqnum":24,
"seqid":"2022B",
"expType":"object",
"object":"TIC206544316_offset_J011403.71-594715.85_i",
"proposer":"Leauthaud",
"program":"Merian",
"RA":18.515488303,
"propid":"2020B-0288",
"dec":-59.7877375539,
"expTime":3.0,
"count":1,
"wait":"False"
},
{
"comment":"--",
"filter":"i",
"seqtot":100,
"seqnum":25,
"seqid":"2022B",
"expType":"object",
"object":"TIC206544316_offset_J011351.14-594746.93_i",
"proposer":"Leauthaud",
"program":"Merian",
"RA":18.4631028047,
"propid":"2020B-0288",
"dec":-59.7963702154,
"expTime":3.0,
"count":1,
"wait":"False"
},
{
"comment":"--",
"filter":"i",
"seqtot":100,
"seqnum":26,
"seqid":"2022B",
"expType":"object",
"object":"TIC206544316_offset_J011345.10-594333.24_i",
"proposer":"Leauthaud",
"program":"Merian",
"RA":18.4379233338,
"propid":"2020B-0288",
"dec":-59.7259004853,
"expTime":3.0,
"count":1,
"wait":"False"
},
{
"comment":"--",
"filter":"i",
"seqtot":100,
"seqnum":27,
"seqid":"2022B",
"expType":"object",
"object":"TIC206544316_offset_J011327.78-594058.52_i",
"proposer":"Leauthaud",
"program":"Merian",
"RA":18.3657518939,
"propid":"2020B-0288",
"dec":-59.6829246584,
"expTime":3.0,
"count":1,
"wait":"False"
},
{
"comment":"--",
"filter":"i",
"seqtot":100,
"seqnum":28,
"seqid":"2022B",
"expType":"object",
"object":"TIC206544316_offset_J011334.22-594502.59_i",
"proposer":"Leauthaud",
"program":"Merian",
"RA":18.3925981316,
"propid":"2020B-0288",
"dec":-59.7507197394,
"expTime":3.0,
"count":1,
"wait":"False"
},
{
"comment":"--",
"filter":"i",
"seqtot":100,
"seqnum":29,
"seqid":"2022B",
"expType":"object",
"object":"TIC206544316_offset_J011330.95-593902.25_i",
"proposer":"Leauthaud",
"program":"Merian",
"RA":18.3789600132,
"propid":"2020B-0288",
"dec":-59.6506275358,
"expTime":3.0,
"count":1,
"wait":"False"
},
{
"comment":"--",
"filter":"i",
"seqtot":100,
"seqnum":30,
"seqid":"2022B",
"expType":"object",
"object":"TIC206544316_offset_J011326.21-593857.77_i",
"proposer":"Leauthaud",
"program":"Merian",
"RA":18.3592360211,
"propid":"2020B-0288",
"dec":-59.6493825682,
"expTime":3.0,
"count":1,
"wait":"False"
},
{
"comment":"--",
"filter":"i",
"seqtot":100,
"seqnum":31,
"seqid":"2022B",
"expType":"object",
"object":"TIC206544316_offset_J011350.39-594723.47_i",
"proposer":"Leauthaud",
"program":"Merian",
"RA":18.4599914525,
"propid":"2020B-0288",
"dec":-59.7898535313,
"expTime":3.0,
"count":1,
"wait":"False"
},
{
"comment":"--",
"filter":"i",
"seqtot":100,
"seqnum":32,
"seqid":"2022B",
"expType":"object",
"object":"TIC206544316_offset_J011352.80-594333.03_i",
"proposer":"Leauthaud",
"program":"Merian",
"RA":18.4700233297,
"propid":"2020B-0288",
"dec":-59.7258436779,
"expTime":3.0,
"count":1,
"wait":"False"
},
{
"comment":"--",
"filter":"i",
"seqtot":100,
"seqnum":33,
"seqid":"2022B",
"expType":"object",
"object":"TIC206544316_offset_J011315.16-594239.50_i",
"proposer":"Leauthaud",
"program":"Merian",
"RA":18.3131951432,
"propid":"2020B-0288",
"dec":-59.7109739797,
"expTime":3.0,
"count":1,
"wait":"False"
},
{
"comment":"--",
"filter":"i",
"seqtot":100,
"seqnum":34,
"seqid":"2022B",
"expType":"object",
"object":"TIC206544316_offset_J011359.25-593952.97_i",
"proposer":"Leauthaud",
"program":"Merian",
"RA":18.4969042489,
"propid":"2020B-0288",
"dec":-59.6647165122,
"expTime":3.0,
"count":1,
"wait":"False"
},
{
"comment":"--",
"filter":"i",
"seqtot":100,
"seqnum":35,
"seqid":"2022B",
"expType":"object",
"object":"TIC206544316_offset_J011322.50-593625.48_i",
"proposer":"Leauthaud",
"program":"Merian",
"RA":18.3437610357,
"propid":"2020B-0288",
"dec":-59.6070791445,
"expTime":3.0,
"count":1,
"wait":"False"
},
{
"comment":"--",
"filter":"i",
"seqtot":100,
"seqnum":36,
"seqid":"2022B",
"expType":"object",
"object":"TIC206544316_offset_J011315.81-594041.11_i",
"proposer":"Leauthaud",
"program":"Merian",
"RA":18.315889985,
"propid":"2020B-0288",
"dec":-59.6780868372,
"expTime":3.0,
"count":1,
"wait":"False"
},
{
"comment":"--",
"filter":"i",
"seqtot":100,
"seqnum":37,
"seqid":"2022B",
"expType":"object",
"object":"TIC206544316_offset_J011355.36-594651.30_i",
"proposer":"Leauthaud",
"program":"Merian",
"RA":18.4806725919,
"propid":"2020B-0288",
"dec":-59.7809170501,
"expTime":3.0,
"count":1,
"wait":"False"
},
{
"comment":"--",
"filter":"i",
"seqtot":100,
"seqnum":38,
"seqid":"2022B",
"expType":"object",
"object":"TIC206544316_offset_J011339.28-593725.71_i",
"proposer":"Leauthaud",
"program":"Merian",
"RA":18.4137052684,
"propid":"2020B-0288",
"dec":-59.6238107534,
"expTime":3.0,
"count":1,
"wait":"False"
},
{
"comment":"--",
"filter":"i",
"seqtot":100,
"seqnum":39,
"seqid":"2022B",
"expType":"object",
"object":"TIC206544316_offset_J011318.55-593842.06_i",
"proposer":"Leauthaud",
"program":"Merian",
"RA":18.3273291657,
"propid":"2020B-0288",
"dec":-59.6450189521,
"expTime":3.0,
"count":1,
"wait":"False"
},
{
"comment":"--",
"filter":"i",
"seqtot":100,
"seqnum":40,
"seqid":"2022B",
"expType":"object",
"object":"TIC206544316_offset_J011325.29-593956.45_i",
"proposer":"Leauthaud",
"program":"Merian",
"RA":18.3553919681,
"propid":"2020B-0288",
"dec":-59.6656818586,
"expTime":3.0,
"count":1,
"wait":"False"
},
{
"comment":"--",
"filter":"i",
"seqtot":100,
"seqnum":41,
"seqid":"2022B",
"expType":"object",
"object":"TIC206544316_offset_J011336.61-594012.57_i",
"proposer":"Leauthaud",
"program":"Merian",
"RA":18.4025540594,
"propid":"2020B-0288",
"dec":-59.6701590913,
"expTime":3.0,
"count":1,
"wait":"False"
},
{
"comment":"--",
"filter":"i",
"seqtot":100,
"seqnum":42,
"seqid":"2022B",
"expType":"object",
"object":"TIC206544316_offset_J011311.47-593849.94_i",
"proposer":"Leauthaud",
"program":"Merian",
"RA":18.2978127017,
"propid":"2020B-0288",
"dec":-59.6472071708,
"expTime":3.0,
"count":1,
"wait":"False"
},
{
"comment":"--",
"filter":"i",
"seqtot":100,
"seqnum":43,
"seqid":"2022B",
"expType":"object",
"object":"TIC206544316_offset_J011347.23-593738.90_i",
"proposer":"Leauthaud",
"program":"Merian",
"RA":18.4468232723,
"propid":"2020B-0288",
"dec":-59.6274744102,
"expTime":3.0,
"count":1,
"wait":"False"
},
{
"comment":"--",
"filter":"i",
"seqtot":100,
"seqnum":44,
"seqid":"2022B",
"expType":"object",
"object":"TIC206544316_offset_J011327.75-593812.41_i",
"proposer":"Leauthaud",
"program":"Merian",
"RA":18.3656533906,
"propid":"2020B-0288",
"dec":-59.6367821849,
"expTime":3.0,
"count":1,
"wait":"False"
},
{
"comment":"--",
"filter":"i",
"seqtot":100,
"seqnum":45,
"seqid":"2022B",
"expType":"object",
"object":"TIC206544316_offset_J011327.24-594421.10_i",
"proposer":"Leauthaud",
"program":"Merian",
"RA":18.3635351256,
"propid":"2020B-0288",
"dec":-59.7391960651,
"expTime":3.0,
"count":1,
"wait":"False"
},
{
"comment":"--",
"filter":"i",
"seqtot":100,
"seqnum":46,
"seqid":"2022B",
"expType":"object",
"object":"TIC206544316_offset_J011335.47-594054.92_i",
"proposer":"Leauthaud",
"program":"Merian",
"RA":18.3978099861,
"propid":"2020B-0288",
"dec":-59.6819228996,
"expTime":3.0,
"count":1,
"wait":"False"
},
{
"comment":"--",
"filter":"i",
"seqtot":100,
"seqnum":47,
"seqid":"2022B",
"expType":"object",
"object":"TIC206544316_offset_J011327.76-594800.28_i",
"proposer":"Leauthaud",
"program":"Merian",
"RA":18.3656870806,
"propid":"2020B-0288",
"dec":-59.800078474,
"expTime":3.0,
"count":1,
"wait":"False"
},
{
"comment":"--",
"filter":"i",
"seqtot":100,
"seqnum":48,
"seqid":"2022B",
"expType":"object",
"object":"TIC206544316_offset_J011329.02-594452.69_i",
"proposer":"Leauthaud",
"program":"Merian",
"RA":18.3709453197,
"propid":"2020B-0288",
"dec":-59.7479698388,
"expTime":3.0,
"count":1,
"wait":"False"
},
{
"comment":"--",
"filter":"i",
"seqtot":100,
"seqnum":49,
"seqid":"2022B",
"expType":"object",
"object":"TIC206544316_offset_J011323.52-594723.02_i",
"proposer":"Leauthaud",
"program":"Merian",
"RA":18.3480209927,
"propid":"2020B-0288",
"dec":-59.7897296559,
"expTime":3.0,
"count":1,
"wait":"False"
},
{
"comment":"--",
"filter":"i",
"seqtot":100,
"seqnum":50,
"seqid":"2022B",
"expType":"object",
"object":"TIC206544316_offset_J011340.89-594622.92_i",
"proposer":"Leauthaud",
"program":"Merian",
"RA":18.4204086221,
"propid":"2020B-0288",
"dec":-59.7730346288,
"expTime":3.0,
"count":1,
"wait":"False"
},
{
"comment":"--",
"filter":"i",
"seqtot":100,
"seqnum":51,
"seqid":"2022B",
"expType":"object",
"object":"TIC206544316_offset_J011328.15-594542.49_i",
"proposer":"Leauthaud",
"program":"Merian",
"RA":18.3673058377,
"propid":"2020B-0288",
"dec":-59.7618050648,
"expTime":3.0,
"count":1,
"wait":"False"
},
{
"comment":"--",
"filter":"i",
"seqtot":100,
"seqnum":52,
"seqid":"2022B",
"expType":"object",
"object":"TIC206544316_offset_J011323.36-594522.61_i",
"proposer":"Leauthaud",
"program":"Merian",
"RA":18.3473418437,
"propid":"2020B-0288",
"dec":-59.7562829459,
"expTime":3.0,
"count":1,
"wait":"False"
},
{
"comment":"--",
"filter":"i",
"seqtot":100,
"seqnum":53,
"seqid":"2022B",
"expType":"object",
"object":"TIC206544316_offset_J011310.49-594351.89_i",
"proposer":"Leauthaud",
"program":"Merian",
"RA":18.2937464121,
"propid":"2020B-0288",
"dec":-59.7310815866,
"expTime":3.0,
"count":1,
"wait":"False"
},
{
"comment":"--",
"filter":"i",
"seqtot":100,
"seqnum":54,
"seqid":"2022B",
"expType":"object",
"object":"TIC206544316_offset_J011317.20-594652.26_i",
"proposer":"Leauthaud",
"program":"Merian",
"RA":18.3217007501,
"propid":"2020B-0288",
"dec":-59.7811859888,
"expTime":3.0,
"count":1,
"wait":"False"
},
{
"comment":"--",
"filter":"i",
"seqtot":100,
"seqnum":55,
"seqid":"2022B",
"expType":"object",
"object":"TIC206544316_offset_J011328.96-593942.83_i",
"proposer":"Leauthaud",
"program":"Merian",
"RA":18.3706896897,
"propid":"2020B-0288",
"dec":-59.6618999733,
"expTime":3.0,
"count":1,
"wait":"False"
},
{
"comment":"--",
"filter":"i",
"seqtot":100,
"seqnum":56,
"seqid":"2022B",
"expType":"object",
"object":"TIC206544316_offset_J011341.15-594416.17_i",
"proposer":"Leauthaud",
"program":"Merian",
"RA":18.4214973696,
"propid":"2020B-0288",
"dec":-59.7378250678,
"expTime":3.0,
"count":1,
"wait":"False"
},
{
"comment":"--",
"filter":"i",
"seqtot":100,
"seqnum":57,
"seqid":"2022B",
"expType":"object",
"object":"TIC206544316_offset_J011336.86-594407.21_i",
"proposer":"Leauthaud",
"program":"Merian",
"RA":18.4035937998,
"propid":"2020B-0288",
"dec":-59.7353368153,
"expTime":3.0,
"count":1,
"wait":"False"
},
{
"comment":"--",
"filter":"i",
"seqtot":100,
"seqnum":58,
"seqid":"2022B",
"expType":"object",
"object":"TIC206544316_offset_J011335.77-594756.73_i",
"proposer":"Leauthaud",
"program":"Merian",
"RA":18.3990515264,
"propid":"2020B-0288",
"dec":-59.7990923934,
"expTime":3.0,
"count":1,
"wait":"False"
},
{
"comment":"--",
"filter":"i",
"seqtot":100,
"seqnum":59,
"seqid":"2022B",
"expType":"object",
"object":"TIC206544316_offset_J011349.58-594857.05_i",
"proposer":"Leauthaud",
"program":"Merian",
"RA":18.4565875217,
"propid":"2020B-0288",
"dec":-59.8158479691,
"expTime":3.0,
"count":1,
"wait":"False"
},
{
"comment":"--",
"filter":"i",
"seqtot":100,
"seqnum":60,
"seqid":"2022B",
"expType":"object",
"object":"TIC206544316_offset_J011342.07-594503.22_i",
"proposer":"Leauthaud",
"program":"Merian",
"RA":18.4253105034,
"propid":"2020B-0288",
"dec":-59.7508956745,
"expTime":3.0,
"count":1,
"wait":"False"
},
{
"comment":"--",
"filter":"i",
"seqtot":100,
"seqnum":61,
"seqid":"2022B",
"expType":"object",
"object":"TIC206544316_offset_J011326.75-594837.64_i",
"proposer":"Leauthaud",
"program":"Merian",
"RA":18.3614993695,
"propid":"2020B-0288",
"dec":-59.8104579371,
"expTime":3.0,
"count":1,
"wait":"False"
},
{
"comment":"--",
"filter":"i",
"seqtot":100,
"seqnum":62,
"seqid":"2022B",
"expType":"object",
"object":"TIC206544316_offset_J011343.64-594649.37_i",
"proposer":"Leauthaud",
"program":"Merian",
"RA":18.4318613879,
"propid":"2020B-0288",
"dec":-59.7803829368,
"expTime":3.0,
"count":1,
"wait":"False"
},
{
"comment":"--",
"filter":"i",
"seqtot":100,
"seqnum":63,
"seqid":"2022B",
"expType":"object",
"object":"TIC206544316_offset_J011311.87-594908.23_i",
"proposer":"Leauthaud",
"program":"Merian",
"RA":18.2994670735,
"propid":"2020B-0288",
"dec":-59.8189547324,
"expTime":3.0,
"count":1,
"wait":"False"
},
{
"comment":"--",
"filter":"i",
"seqtot":100,
"seqnum":64,
"seqid":"2022B",
"expType":"object",
"object":"TIC206544316_offset_J011325.12-594010.64_i",
"proposer":"Leauthaud",
"program":"Merian",
"RA":18.3546969146,
"propid":"2020B-0288",
"dec":-59.6696226315,
"expTime":3.0,
"count":1,
"wait":"False"
},
{
"comment":"--",
"filter":"i",
"seqtot":100,
"seqnum":65,
"seqid":"2022B",
"expType":"object",
"object":"TIC206544316_offset_J011330.95-594142.86_i",
"proposer":"Leauthaud",
"program":"Merian",
"RA":18.3789880628,
"propid":"2020B-0288",
"dec":-59.6952391209,
"expTime":3.0,
"count":1,
"wait":"False"
},
{
"comment":"--",
"filter":"i",
"seqtot":100,
"seqnum":66,
"seqid":"2022B",
"expType":"object",
"object":"TIC206544316_offset_J011358.26-594731.97_i",
"proposer":"Leauthaud",
"program":"Merian",
"RA":18.4927872849,
"propid":"2020B-0288",
"dec":-59.7922143697,
"expTime":3.0,
"count":1,
"wait":"False"
},
{
"comment":"--",
"filter":"i",
"seqtot":100,
"seqnum":67,
"seqid":"2022B",
"expType":"object",
"object":"TIC206544316_offset_J011337.89-594058.94_i",
"proposer":"Leauthaud",
"program":"Merian",
"RA":18.4079067041,
"propid":"2020B-0288",
"dec":-59.6830415724,
"expTime":3.0,
"count":1,
"wait":"False"
},
{
"comment":"--",
"filter":"i",
"seqtot":100,
"seqnum":68,
"seqid":"2022B",
"expType":"object",
"object":"TIC206544316_offset_J011320.43-594200.22_i",
"proposer":"Leauthaud",
"program":"Merian",
"RA":18.3351632307,
"propid":"2020B-0288",
"dec":-59.7000637341,
"expTime":3.0,
"count":1,
"wait":"False"
},
{
"comment":"--",
"filter":"i",
"seqtot":100,
"seqnum":69,
"seqid":"2022B",
"expType":"object",
"object":"TIC206544316_offset_J011346.76-593924.43_i",
"proposer":"Leauthaud",
"program":"Merian",
"RA":18.4448409494,
"propid":"2020B-0288",
"dec":-59.6567866086,
"expTime":3.0,
"count":1,
"wait":"False"
},
{
"comment":"--",
"filter":"i",
"seqtot":100,
"seqnum":70,
"seqid":"2022B",
"expType":"object",
"object":"TIC206544316_offset_J011333.07-594322.27_i",
"proposer":"Leauthaud",
"program":"Merian",
"RA":18.3878324837,
"propid":"2020B-0288",
"dec":-59.7228528976,
"expTime":3.0,
"count":1,
"wait":"False"
},
{
"comment":"--",
"filter":"i",
"seqtot":100,
"seqnum":71,
"seqid":"2022B",
"expType":"object",
"object":"TIC206544316_offset_J011358.14-594456.15_i",
"proposer":"Leauthaud",
"program":"Merian",
"RA":18.4922672892,
"propid":"2020B-0288",
"dec":-59.748933047,
"expTime":3.0,
"count":1,
"wait":"False"
},
{
"comment":"--",
"filter":"i",
"seqtot":100,
"seqnum":72,
"seqid":"2022B",
"expType":"object",
"object":"TIC206544316_offset_J011326.29-594222.62_i",
"proposer":"Leauthaud",
"program":"Merian",
"RA":18.359563907,
"propid":"2020B-0288",
"dec":-59.7062841916,
"expTime":3.0,
"count":1,
"wait":"False"
},
{
"comment":"--",
"filter":"i",
"seqtot":100,
"seqnum":73,
"seqid":"2022B",
"expType":"object",
"object":"TIC206544316_offset_J011339.25-594834.24_i",
"proposer":"Leauthaud",
"program":"Merian",
"RA":18.4135808965,
"propid":"2020B-0288",
"dec":-59.8095111777,
"expTime":3.0,
"count":1,
"wait":"False"
},
{
"comment":"--",
"filter":"i",
"seqtot":100,
"seqnum":74,
"seqid":"2022B",
"expType":"object",
"object":"TIC206544316_offset_J011352.92-594952.42_i",
"proposer":"Leauthaud",
"program":"Merian",
"RA":18.4705081683,
"propid":"2020B-0288",
"dec":-59.8312280138,
"expTime":3.0,
"count":1,
"wait":"False"
},
{
"comment":"--",
"filter":"i",
"seqtot":100,
"seqnum":75,
"seqid":"2022B",
"expType":"object",
"object":"TIC206544316_offset_J011317.84-594931.08_i",
"proposer":"Leauthaud",
"program":"Merian",
"RA":18.3243337509,
"propid":"2020B-0288",
"dec":-59.8253006658,
"expTime":3.0,
"count":1,
"wait":"False"
},
{
"comment":"--",
"filter":"i",
"seqtot":100,
"seqnum":76,
"seqid":"2022B",
"expType":"object",
"object":"TIC206544316_offset_J011403.47-594825.82_i",
"proposer":"Leauthaud",
"program":"Merian",
"RA":18.5144603746,
"propid":"2020B-0288",
"dec":-59.8071730553,
"expTime":3.0,
"count":1,
"wait":"False"
},
{
"comment":"--",
"filter":"i",
"seqtot":100,
"seqnum":77,
"seqid":"2022B",
"expType":"object",
"object":"TIC206544316_offset_J011325.18-595029.32_i",
"proposer":"Leauthaud",
"program":"Merian",
"RA":18.3549493781,
"propid":"2020B-0288",
"dec":-59.8414785655,
"expTime":3.0,
"count":1,
"wait":"False"
},
{
"comment":"--",
"filter":"i",
"seqtot":100,
"seqnum":78,
"seqid":"2022B",
"expType":"object",
"object":"TIC206544316_offset_J011321.11-594548.89_i",
"proposer":"Leauthaud",
"program":"Merian",
"RA":18.3379698001,
"propid":"2020B-0288",
"dec":-59.7635829683,
"expTime":3.0,
"count":1,
"wait":"False"
},
{
"comment":"--",
"filter":"i",
"seqtot":100,
"seqnum":79,
"seqid":"2022B",
"expType":"object",
"object":"TIC206544316_offset_J011320.46-594031.36_i",
"proposer":"Leauthaud",
"program":"Merian",
"RA":18.3352881939,
"propid":"2020B-0288",
"dec":-59.6753801241,
"expTime":3.0,
"count":1,
"wait":"False"
},
{
"comment":"--",
"filter":"i",
"seqtot":100,
"seqnum":80,
"seqid":"2022B",
"expType":"object",
"object":"TIC206544316_offset_J011326.25-594504.80_i",
"proposer":"Leauthaud",
"program":"Merian",
"RA":18.3594036466,
"propid":"2020B-0288",
"dec":-59.7513349068,
"expTime":3.0,
"count":1,
"wait":"False"
},
{
"comment":"--",
"filter":"i",
"seqtot":100,
"seqnum":81,
"seqid":"2022B",
"expType":"object",
"object":"TIC206544316_offset_J011343.93-594734.70_i",
"proposer":"Leauthaud",
"program":"Merian",
"RA":18.433063391,
"propid":"2020B-0288",
"dec":-59.7929736899,
"expTime":3.0,
"count":1,
"wait":"False"
},
{
"comment":"--",
"filter":"i",
"seqtot":100,
"seqnum":82,
"seqid":"2022B",
"expType":"object",
"object":"TIC206544316_offset_J011327.15-594539.78_i",
"proposer":"Leauthaud",
"program":"Merian",
"RA":18.3631495248,
"propid":"2020B-0288",
"dec":-59.7610520988,
"expTime":3.0,
"count":1,
"wait":"False"
},
{
"comment":"--",
"filter":"i",
"seqtot":100,
"seqnum":83,
"seqid":"2022B",
"expType":"object",
"object":"TIC206544316_offset_J011325.54-595013.40_i",
"proposer":"Leauthaud",
"program":"Merian",
"RA":18.3564252076,
"propid":"2020B-0288",
"dec":-59.837056078,
"expTime":3.0,
"count":1,
"wait":"False"
},
{
"comment":"--",
"filter":"i",
"seqtot":100,
"seqnum":84,
"seqid":"2022B",
"expType":"object",
"object":"TIC206544316_offset_J011406.43-594939.70_i",
"proposer":"Leauthaud",
"program":"Merian",
"RA":18.5267955689,
"propid":"2020B-0288",
"dec":-59.8276965789,
"expTime":3.0,
"count":1,
"wait":"False"
},
{
"comment":"--",
"filter":"i",
"seqtot":100,
"seqnum":85,
"seqid":"2022B",
"expType":"object",
"object":"TIC206544316_offset_J011351.59-594456.81_i",
"proposer":"Leauthaud",
"program":"Merian",
"RA":18.4649600783,
"propid":"2020B-0288",
"dec":-59.749115619,
"expTime":3.0,
"count":1,
"wait":"False"
},
{
"comment":"--",
"filter":"i",
"seqtot":100,
"seqnum":86,
"seqid":"2022B",
"expType":"object",
"object":"TIC206544316_offset_J011325.78-594752.67_i",
"proposer":"Leauthaud",
"program":"Merian",
"RA":18.3574366766,
"propid":"2020B-0288",
"dec":-59.7979651057,
"expTime":3.0,
"count":1,
"wait":"False"
},
{
"comment":"--",
"filter":"i",
"seqtot":100,
"seqnum":87,
"seqid":"2022B",
"expType":"object",
"object":"TIC206544316_offset_J011401.59-594502.80_i",
"proposer":"Leauthaud",
"program":"Merian",
"RA":18.5066385021,
"propid":"2020B-0288",
"dec":-59.7507802335,
"expTime":3.0,
"count":1,
"wait":"False"
},
{
"comment":"--",
"filter":"i",
"seqtot":100,
"seqnum":88,
"seqid":"2022B",
"expType":"object",
"object":"TIC206544316_offset_J011322.24-595011.66_i",
"proposer":"Leauthaud",
"program":"Merian",
"RA":18.3426737098,
"propid":"2020B-0288",
"dec":-59.836574885,
"expTime":3.0,
"count":1,
"wait":"False"
},
{
"comment":"--",
"filter":"i",
"seqtot":100,
"seqnum":89,
"seqid":"2022B",
"expType":"object",
"object":"TIC206544316_offset_J011354.66-594455.29_i",
"proposer":"Leauthaud",
"program":"Merian",
"RA":18.4777604813,
"propid":"2020B-0288",
"dec":-59.7486924748,
"expTime":3.0,
"count":1,
"wait":"False"
},
{
"comment":"--",
"filter":"i",
"seqtot":100,
"seqnum":90,
"seqid":"2022B",
"expType":"object",
"object":"TIC206544316_offset_J011329.28-593957.26_i",
"proposer":"Leauthaud",
"program":"Merian",
"RA":18.3720093459,
"propid":"2020B-0288",
"dec":-59.6659075281,
"expTime":3.0,
"count":1,
"wait":"False"
},
{
"comment":"--",
"filter":"i",
"seqtot":100,
"seqnum":91,
"seqid":"2022B",
"expType":"object",
"object":"TIC206544316_offset_J011333.94-594629.26_i",
"proposer":"Leauthaud",
"program":"Merian",
"RA":18.3914514174,
"propid":"2020B-0288",
"dec":-59.7747965775,
"expTime":3.0,
"count":1,
"wait":"False"
},
{
"comment":"--",
"filter":"i",
"seqtot":100,
"seqnum":92,
"seqid":"2022B",
"expType":"object",
"object":"TIC206544316_offset_J011331.78-594047.99_i",
"proposer":"Leauthaud",
"program":"Merian",
"RA":18.3824299257,
"propid":"2020B-0288",
"dec":-59.679999661,
"expTime":3.0,
"count":1,
"wait":"False"
},
{
"comment":"--",
"filter":"i",
"seqtot":100,
"seqnum":93,
"seqid":"2022B",
"expType":"object",
"object":"TIC206544316_offset_J011354.24-593831.28_i",
"proposer":"Leauthaud",
"program":"Merian",
"RA":18.476029497,
"propid":"2020B-0288",
"dec":-59.6420226936,
"expTime":3.0,
"count":1,
"wait":"False"
},
{
"comment":"--",
"filter":"i",
"seqtot":100,
"seqnum":94,
"seqid":"2022B",
"expType":"object",
"object":"TIC206544316_offset_J011327.98-594145.00_i",
"proposer":"Leauthaud",
"program":"Merian",
"RA":18.3665956891,
"propid":"2020B-0288",
"dec":-59.6958333878,
"expTime":3.0,
"count":1,
"wait":"False"
},
{
"comment":"--",
"filter":"i",
"seqtot":100,
"seqnum":95,
"seqid":"2022B",
"expType":"object",
"object":"TIC206544316_offset_J011336.98-594338.40_i",
"proposer":"Leauthaud",
"program":"Merian",
"RA":18.40412031,
"propid":"2020B-0288",
"dec":-59.727333537,
"expTime":3.0,
"count":1,
"wait":"False"
},
{
"comment":"--",
"filter":"i",
"seqtot":100,
"seqnum":96,
"seqid":"2022B",
"expType":"object",
"object":"TIC206544316_offset_J011327.74-594848.97_i",
"proposer":"Leauthaud",
"program":"Merian",
"RA":18.3655898495,
"propid":"2020B-0288",
"dec":-59.8136032806,
"expTime":3.0,
"count":1,
"wait":"False"
},
{
"comment":"--",
"filter":"i",
"seqtot":100,
"seqnum":97,
"seqid":"2022B",
"expType":"object",
"object":"TIC206544316_offset_J011356.41-594439.06_i",
"proposer":"Leauthaud",
"program":"Merian",
"RA":18.4850667362,
"propid":"2020B-0288",
"dec":-59.7441834759,
"expTime":3.0,
"count":1,
"wait":"False"
},
{
"comment":"--",
"filter":"i",
"seqtot":100,
"seqnum":98,
"seqid":"2022B",
"expType":"object",
"object":"TIC206544316_offset_J011328.14-594515.73_i",
"proposer":"Leauthaud",
"program":"Merian",
"RA":18.3672561517,
"propid":"2020B-0288",
"dec":-59.7543696539,
"expTime":3.0,
"count":1,
"wait":"False"
},
{
"comment":"--",
"filter":"i",
"seqtot":100,
"seqnum":99,
"seqid":"2022B",
"expType":"object",
"object":"TIC206544316_offset_J011355.02-594544.51_i",
"proposer":"Leauthaud",
"program":"Merian",
"RA":18.4792522563,
"propid":"2020B-0288",
"dec":-59.7623642542,
"expTime":3.0,
"count":1,
"wait":"False"
},
{
"comment":"--",
"filter":"i",
"seqtot":100,
"seqnum":100,
"seqid":"2022B",
"expType":"object",
"object":"TIC206544316_offset_J011342.07-593923.36_i",
"proposer":"Leauthaud",
"program":"Merian",
"RA":18.4253172324,
"propid":"2020B-0288",
"dec":-59.6564892236,
"expTime":3.0,
"count":1,
"wait":"False"
}
]