[
{
"comment":"OneMinuteFocusExposure",
"filter":"g",
"seqtot":13,
"seqnum":1,
"seqid":"2022B",
"expType":"object",
"object":"1minexp_000",
"proposer":"Leauthaud",
"program":"Merian",
"RA":345.3551208,
"propid":"2020B-0288",
"dec":-34.2113545,
"expTime":60.0,
"count":1,
"wait":"False"
},
{
"comment":"--",
"filter":"g",
"seqtot":13,
"seqnum":2,
"seqid":"2022B",
"expType":"object",
"object":"GAMA5275222_J230125.22-341240.87_g",
"proposer":"Leauthaud",
"program":"Merian",
"RA":345.3551208,
"propid":"2020B-0288",
"dec":-34.2113545,
"expTime":300.0,
"count":1,
"wait":"False"
},
{
"comment":"--",
"filter":"g",
"seqtot":13,
"seqnum":3,
"seqid":"2022B",
"expType":"object",
"object":"GAMA5275222_J230149.19-341602.09_g",
"proposer":"Leauthaud",
"program":"Merian",
"RA":345.454997533,
"propid":"2020B-0288",
"dec":-34.2672486521,
"expTime":300.0,
"count":1,
"wait":"False"
},
{
"comment":"--",
"filter":"g",
"seqtot":13,
"seqnum":4,
"seqid":"2022B",
"expType":"object",
"object":"GAMA5275222_J230135.30-340655.22_g",
"proposer":"Leauthaud",
"program":"Merian",
"RA":345.3970944333,
"propid":"2020B-0288",
"dec":-34.1153402731,
"expTime":300.0,
"count":1,
"wait":"False"
},
{
"comment":"--",
"filter":"g",
"seqtot":13,
"seqnum":5,
"seqid":"2022B",
"expType":"object",
"object":"GAMA5275222_J230109.37-340622.41_g",
"proposer":"Leauthaud",
"program":"Merian",
"RA":345.2890611061,
"propid":"2020B-0288",
"dec":-34.1062252247,
"expTime":300.0,
"count":1,
"wait":"False"
},
{
"comment":"--",
"filter":"g",
"seqtot":13,
"seqnum":6,
"seqid":"2022B",
"expType":"object",
"object":"GAMA5275222_J230117.35-340935.65_g",
"proposer":"Leauthaud",
"program":"Merian",
"RA":345.3223284494,
"propid":"2020B-0288",
"dec":-34.1599054964,
"expTime":300.0,
"count":1,
"wait":"False"
},
{
"comment":"--",
"filter":"g",
"seqtot":13,
"seqnum":7,
"seqid":"2022B",
"expType":"object",
"object":"GAMA5275222_J230146.99-341349.77_g",
"proposer":"Leauthaud",
"program":"Merian",
"RA":345.4457921582,
"propid":"2020B-0288",
"dec":-34.2304936403,
"expTime":300.0,
"count":1,
"wait":"False"
},
{
"comment":"--",
"filter":"g",
"seqtot":13,
"seqnum":8,
"seqid":"2022B",
"expType":"object",
"object":"GAMA5275222_J230115.25-341226.89_g",
"proposer":"Leauthaud",
"program":"Merian",
"RA":345.3135737591,
"propid":"2020B-0288",
"dec":-34.2074720631,
"expTime":300.0,
"count":1,
"wait":"False"
},
{
"comment":"--",
"filter":"g",
"seqtot":13,
"seqnum":9,
"seqid":"2022B",
"expType":"object",
"object":"GAMA5275222_J230111.39-341231.43_g",
"proposer":"Leauthaud",
"program":"Merian",
"RA":345.2974716219,
"propid":"2020B-0288",
"dec":-34.2087320619,
"expTime":300.0,
"count":1,
"wait":"False"
},
{
"comment":"--",
"filter":"g",
"seqtot":13,
"seqnum":10,
"seqid":"2022B",
"expType":"object",
"object":"GAMA5275222_J230111.18-341415.63_g",
"proposer":"Leauthaud",
"program":"Merian",
"RA":345.2966200256,
"propid":"2020B-0288",
"dec":-34.237675576,
"expTime":300.0,
"count":1,
"wait":"False"
},
{
"comment":"--",
"filter":"g",
"seqtot":13,
"seqnum":11,
"seqid":"2022B",
"expType":"object",
"object":"GAMA5275222_J230108.56-341901.72_g",
"proposer":"Leauthaud",
"program":"Merian",
"RA":345.2856960391,
"propid":"2020B-0288",
"dec":-34.317145448,
"expTime":300.0,
"count":1,
"wait":"False"
},
{
"comment":"--",
"filter":"g",
"seqtot":13,
"seqnum":12,
"seqid":"2022B",
"expType":"object",
"object":"GAMA5275222_J230120.17-340959.19_g",
"proposer":"Leauthaud",
"program":"Merian",
"RA":345.3340825148,
"propid":"2020B-0288",
"dec":-34.1664424517,
"expTime":300.0,
"count":1,
"wait":"False"
},
{
"comment":"--",
"filter":"g",
"seqtot":13,
"seqnum":13,
"seqid":"2022B",
"expType":"object",
"object":"GAMA5275222_J230141.74-340757.18_g",
"proposer":"Leauthaud",
"program":"Merian",
"RA":345.4239487697,
"propid":"2020B-0288",
"dec":-34.1325516354,
"expTime":300.0,
"count":1,
"wait":"False"
}
]