[
{
"comment":"OneMinuteFocusExposure",
"filter":"g",
"seqtot":13,
"seqnum":1,
"seqid":"2022B",
"expType":"object",
"object":"1minexp_000",
"proposer":"Leauthaud",
"program":"Merian",
"RA":339.824962,
"propid":"2020B-0288",
"dec":-34.0506528,
"expTime":60.0,
"count":1,
"wait":"False"
},
{
"comment":"--",
"filter":"g",
"seqtot":13,
"seqnum":2,
"seqid":"2022B",
"expType":"object",
"object":"GAMA5197149_J223917.99-340302.35_g",
"proposer":"Leauthaud",
"program":"Merian",
"RA":339.824962,
"propid":"2020B-0288",
"dec":-34.0506528,
"expTime":300.0,
"count":1,
"wait":"False"
},
{
"comment":"--",
"filter":"g",
"seqtot":13,
"seqnum":3,
"seqid":"2022B",
"expType":"object",
"object":"GAMA5197149_J223915.73-340753.89_g",
"proposer":"Leauthaud",
"program":"Merian",
"RA":339.8155674382,
"propid":"2020B-0288",
"dec":-34.1316365826,
"expTime":300.0,
"count":1,
"wait":"False"
},
{
"comment":"--",
"filter":"g",
"seqtot":13,
"seqnum":4,
"seqid":"2022B",
"expType":"object",
"object":"GAMA5197149_J223920.72-335728.13_g",
"proposer":"Leauthaud",
"program":"Merian",
"RA":339.8363366466,
"propid":"2020B-0288",
"dec":-33.9578145814,
"expTime":300.0,
"count":1,
"wait":"False"
},
{
"comment":"--",
"filter":"g",
"seqtot":13,
"seqnum":5,
"seqid":"2022B",
"expType":"object",
"object":"GAMA5197149_J223937.14-340238.40_g",
"proposer":"Leauthaud",
"program":"Merian",
"RA":339.9047916213,
"propid":"2020B-0288",
"dec":-34.0440006707,
"expTime":300.0,
"count":1,
"wait":"False"
},
{
"comment":"--",
"filter":"g",
"seqtot":13,
"seqnum":6,
"seqid":"2022B",
"expType":"object",
"object":"GAMA5197149_J223915.91-340424.16_g",
"proposer":"Leauthaud",
"program":"Merian",
"RA":339.8163253988,
"propid":"2020B-0288",
"dec":-34.0733803719,
"expTime":300.0,
"count":1,
"wait":"False"
},
{
"comment":"--",
"filter":"g",
"seqtot":13,
"seqnum":7,
"seqid":"2022B",
"expType":"object",
"object":"GAMA5197149_J223927.41-340810.26_g",
"proposer":"Leauthaud",
"program":"Merian",
"RA":339.8642363653,
"propid":"2020B-0288",
"dec":-34.1361854336,
"expTime":300.0,
"count":1,
"wait":"False"
},
{
"comment":"--",
"filter":"g",
"seqtot":13,
"seqnum":8,
"seqid":"2022B",
"expType":"object",
"object":"GAMA5197149_J223900.49-340847.62_g",
"proposer":"Leauthaud",
"program":"Merian",
"RA":339.7520511081,
"propid":"2020B-0288",
"dec":-34.1465632287,
"expTime":300.0,
"count":1,
"wait":"False"
},
{
"comment":"--",
"filter":"g",
"seqtot":13,
"seqnum":9,
"seqid":"2022B",
"expType":"object",
"object":"GAMA5197149_J223852.10-335900.37_g",
"proposer":"Leauthaud",
"program":"Merian",
"RA":339.7171019956,
"propid":"2020B-0288",
"dec":-33.983438142,
"expTime":300.0,
"count":1,
"wait":"False"
},
{
"comment":"--",
"filter":"g",
"seqtot":13,
"seqnum":10,
"seqid":"2022B",
"expType":"object",
"object":"GAMA5197149_J223900.51-335933.03_g",
"proposer":"Leauthaud",
"program":"Merian",
"RA":339.7521292776,
"propid":"2020B-0288",
"dec":-33.9925094216,
"expTime":300.0,
"count":1,
"wait":"False"
},
{
"comment":"--",
"filter":"g",
"seqtot":13,
"seqnum":11,
"seqid":"2022B",
"expType":"object",
"object":"GAMA5197149_J223934.13-340258.36_g",
"proposer":"Leauthaud",
"program":"Merian",
"RA":339.8922233533,
"propid":"2020B-0288",
"dec":-34.0495456002,
"expTime":300.0,
"count":1,
"wait":"False"
},
{
"comment":"--",
"filter":"g",
"seqtot":13,
"seqnum":12,
"seqid":"2022B",
"expType":"object",
"object":"GAMA5197149_J223939.03-335924.05_g",
"proposer":"Leauthaud",
"program":"Merian",
"RA":339.9126569254,
"propid":"2020B-0288",
"dec":-33.9900162874,
"expTime":300.0,
"count":1,
"wait":"False"
},
{
"comment":"--",
"filter":"g",
"seqtot":13,
"seqnum":13,
"seqid":"2022B",
"expType":"object",
"object":"GAMA5197149_J223925.60-340340.66_g",
"proposer":"Leauthaud",
"program":"Merian",
"RA":339.8566858796,
"propid":"2020B-0288",
"dec":-34.0612955104,
"expTime":300.0,
"count":1,
"wait":"False"
}
]