[
{
"comment":"OneMinuteFocusExposure",
"filter":"g",
"seqtot":13,
"seqnum":1,
"seqid":"2022B",
"expType":"object",
"object":"1minexp_000",
"proposer":"Leauthaud",
"program":"Merian",
"RA":343.2688411,
"propid":"2020B-0288",
"dec":-33.9772443,
"expTime":60.0,
"count":1,
"wait":"False"
},
{
"comment":"--",
"filter":"g",
"seqtot":13,
"seqnum":2,
"seqid":"2022B",
"expType":"object",
"object":"GAMA5240292_J225304.52-335838.07_g",
"proposer":"Leauthaud",
"program":"Merian",
"RA":343.2688411,
"propid":"2020B-0288",
"dec":-33.9772443,
"expTime":300.0,
"count":1,
"wait":"False"
},
{
"comment":"--",
"filter":"g",
"seqtot":13,
"seqnum":3,
"seqid":"2022B",
"expType":"object",
"object":"GAMA5240292_J225302.39-340412.64_g",
"proposer":"Leauthaud",
"program":"Merian",
"RA":343.2599846809,
"propid":"2020B-0288",
"dec":-34.0701799077,
"expTime":300.0,
"count":1,
"wait":"False"
},
{
"comment":"--",
"filter":"g",
"seqtot":13,
"seqnum":4,
"seqid":"2022B",
"expType":"object",
"object":"GAMA5240292_J225255.07-335440.98_g",
"proposer":"Leauthaud",
"program":"Merian",
"RA":343.2294794647,
"propid":"2020B-0288",
"dec":-33.9113854333,
"expTime":300.0,
"count":1,
"wait":"False"
},
{
"comment":"--",
"filter":"g",
"seqtot":13,
"seqnum":5,
"seqid":"2022B",
"expType":"object",
"object":"GAMA5240292_J225326.48-340003.93_g",
"proposer":"Leauthaud",
"program":"Merian",
"RA":343.3603676202,
"propid":"2020B-0288",
"dec":-34.0010937186,
"expTime":300.0,
"count":1,
"wait":"False"
},
{
"comment":"--",
"filter":"g",
"seqtot":13,
"seqnum":6,
"seqid":"2022B",
"expType":"object",
"object":"GAMA5240292_J225258.30-335352.88_g",
"proposer":"Leauthaud",
"program":"Merian",
"RA":343.2429391491,
"propid":"2020B-0288",
"dec":-33.8980249858,
"expTime":300.0,
"count":1,
"wait":"False"
},
{
"comment":"--",
"filter":"g",
"seqtot":13,
"seqnum":7,
"seqid":"2022B",
"expType":"object",
"object":"GAMA5240292_J225243.39-335527.01_g",
"proposer":"Leauthaud",
"program":"Merian",
"RA":343.1807953244,
"propid":"2020B-0288",
"dec":-33.9241721092,
"expTime":300.0,
"count":1,
"wait":"False"
},
{
"comment":"--",
"filter":"g",
"seqtot":13,
"seqnum":8,
"seqid":"2022B",
"expType":"object",
"object":"GAMA5240292_J225307.67-335756.56_g",
"proposer":"Leauthaud",
"program":"Merian",
"RA":343.2819937095,
"propid":"2020B-0288",
"dec":-33.9657123613,
"expTime":300.0,
"count":1,
"wait":"False"
},
{
"comment":"--",
"filter":"g",
"seqtot":13,
"seqnum":9,
"seqid":"2022B",
"expType":"object",
"object":"GAMA5240292_J225317.54-340228.08_g",
"proposer":"Leauthaud",
"program":"Merian",
"RA":343.3231225315,
"propid":"2020B-0288",
"dec":-34.041134597,
"expTime":300.0,
"count":1,
"wait":"False"
},
{
"comment":"--",
"filter":"g",
"seqtot":13,
"seqnum":10,
"seqid":"2022B",
"expType":"object",
"object":"GAMA5240292_J225318.55-335311.82_g",
"proposer":"Leauthaud",
"program":"Merian",
"RA":343.3273170509,
"propid":"2020B-0288",
"dec":-33.886617837,
"expTime":300.0,
"count":1,
"wait":"False"
},
{
"comment":"--",
"filter":"g",
"seqtot":13,
"seqnum":11,
"seqid":"2022B",
"expType":"object",
"object":"GAMA5240292_J225313.11-340400.89_g",
"proposer":"Leauthaud",
"program":"Merian",
"RA":343.3046287866,
"propid":"2020B-0288",
"dec":-34.0669157737,
"expTime":300.0,
"count":1,
"wait":"False"
},
{
"comment":"--",
"filter":"g",
"seqtot":13,
"seqnum":12,
"seqid":"2022B",
"expType":"object",
"object":"GAMA5240292_J225309.99-340207.74_g",
"proposer":"Leauthaud",
"program":"Merian",
"RA":343.2916419731,
"propid":"2020B-0288",
"dec":-34.0354839946,
"expTime":300.0,
"count":1,
"wait":"False"
},
{
"comment":"--",
"filter":"g",
"seqtot":13,
"seqnum":13,
"seqid":"2022B",
"expType":"object",
"object":"GAMA5240292_J225326.77-335558.89_g",
"proposer":"Leauthaud",
"program":"Merian",
"RA":343.3615576621,
"propid":"2020B-0288",
"dec":-33.9330262901,
"expTime":300.0,
"count":1,
"wait":"False"
}
]