[
{
"object":"1minexp_000",
"comment":"OneMinuteFocusExposure",
"filter":"N70",
"seqtot":7,
"seqnum":1,
"seqid":"S2021B",
"expType":"object",
"proposer":"Leauthaud",
"program":"Merian",
"RA":343.4842572052,
"propid":"2020B-0288",
"dec":2.4427677972,
"expTime":60.0,
"count":1,
"wait":false
},
{
"object":"VVDSearly_J225356.22+022633.96_N70",
"comment":"--",
"filter":"N70",
"seqtot":7,
"seqnum":2,
"seqid":"S2021B",
"expType":"object",
"proposer":"Leauthaud",
"program":"Merian",
"RA":343.4842572052,
"propid":"2020B-0288",
"dec":2.4427677972,
"expTime":600.0,
"count":1,
"wait":false
},
{
"object":"VVDSearly_J225506.02+023127.06_N70",
"comment":"--",
"filter":"N70",
"seqtot":7,
"seqnum":3,
"seqid":"S2021B",
"expType":"object",
"proposer":"Leauthaud",
"program":"Merian",
"RA":343.7751114805,
"propid":"2020B-0288",
"dec":2.5241851526,
"expTime":600.0,
"count":1,
"wait":false
},
{
"object":"VVDSearly_J225616.58+023425.70_N70",
"comment":"--",
"filter":"N70",
"seqtot":7,
"seqnum":4,
"seqid":"S2021B",
"expType":"object",
"proposer":"Leauthaud",
"program":"Merian",
"RA":344.069083573,
"propid":"2020B-0288",
"dec":2.5738063154,
"expTime":600.0,
"count":1,
"wait":false
},
{
"object":"VVDSearly_J225727.13+023724.74_N70",
"comment":"--",
"filter":"N70",
"seqtot":7,
"seqnum":5,
"seqid":"S2021B",
"expType":"object",
"proposer":"Leauthaud",
"program":"Merian",
"RA":344.3630660865,
"propid":"2020B-0288",
"dec":2.6235396677,
"expTime":600.0,
"count":1,
"wait":false
},
{
"object":"VVDSearly_J225135.23+010207.45_N70",
"comment":"--",
"filter":"N70",
"seqtot":7,
"seqnum":6,
"seqid":"S2021B",
"expType":"object",
"proposer":"Leauthaud",
"program":"Merian",
"RA":342.8968214069,
"propid":"2020B-0288",
"dec":1.0354035705,
"expTime":600.0,
"count":1,
"wait":false
},
{
"object":"VVDSearly_J224653.48+010725.02_N70",
"comment":"--",
"filter":"N70",
"seqtot":7,
"seqnum":7,
"seqid":"S2021B",
"expType":"object",
"proposer":"Leauthaud",
"program":"Merian",
"RA":341.7228613204,
"propid":"2020B-0288",
"dec":1.1236190385,
"expTime":600.0,
"count":1,
"wait":false
}
]