[
{
"comment":"--",
"filter":"N70",
"seqtot":6,
"seqnum":1,
"seqid":"TEST",
"expType":"science",
"object":"GAMA_J090542.12-004915.96_N70",
"proposer":"LeathaudGreene",
"program":"Merian",
"RA":136.4255024822,
"propid":"2020B-0288",
"dec":-0.8211026341,
"expTime":600.0,
"count":1
},
{
"comment":"--",
"filter":"N70",
"seqtot":6,
"seqnum":2,
"seqid":"TEST",
"expType":"science",
"object":"GAMA_J090652.65-005141.42_N70",
"proposer":"LeathaudGreene",
"program":"Merian",
"RA":136.7194010859,
"propid":"2020B-0288",
"dec":-0.8615058158,
"expTime":600.0,
"count":1
},
{
"comment":"--",
"filter":"N70",
"seqtot":6,
"seqnum":3,
"seqid":"TEST",
"expType":"science",
"object":"GAMA_J090945.03-004411.67_N70",
"proposer":"LeathaudGreene",
"program":"Merian",
"RA":137.4376522707,
"propid":"2020B-0288",
"dec":-0.736575958,
"expTime":600.0,
"count":1
},
{
"comment":"--",
"filter":"N70",
"seqtot":6,
"seqnum":4,
"seqid":"TEST",
"expType":"science",
"object":"GAMA_J091054.86-004805.93_N70",
"proposer":"LeathaudGreene",
"program":"Merian",
"RA":137.728602419,
"propid":"2020B-0288",
"dec":-0.8016494428,
"expTime":600.0,
"count":1
},
{
"comment":"--",
"filter":"N70",
"seqtot":6,
"seqnum":5,
"seqid":"TEST",
"expType":"science",
"object":"GAMA_J091205.40-005033.19_N70",
"proposer":"LeathaudGreene",
"program":"Merian",
"RA":138.0225267398,
"propid":"2020B-0288",
"dec":-0.8425532662,
"expTime":600.0,
"count":1
},
{
"comment":"--",
"filter":"N70",
"seqtot":6,
"seqnum":6,
"seqid":"TEST",
"expType":"science",
"object":"GAMA_J091315.94-005301.60_N70",
"proposer":"LeathaudGreene",
"program":"Merian",
"RA":138.3164310161,
"propid":"2020B-0288",
"dec":-0.8837782317,
"expTime":600.0,
"count":1
}
]