[
{
"object":"GAMA_J093236.82+021554.96_N708",
"comment":"--",
"filter":"N708",
"seqtot":6,
"seqnum":1,
"seqid":"S2021A",
"expType":"object",
"proposer":"Leauthaud",
"program":"Merian",
"RA":143.1534577926,
"propid":"2020B-0288",
"dec":2.265268839,
"expTime":600.0,
"count":1,
"wait":"False"
},
{
"object":"GAMA_J093535.70+022328.18_N708",
"comment":"--",
"filter":"N708",
"seqtot":6,
"seqnum":2,
"seqid":"S2021A",
"expType":"object",
"proposer":"Leauthaud",
"program":"Merian",
"RA":143.8987772904,
"propid":"2020B-0288",
"dec":2.3911635345,
"expTime":600.0,
"count":1,
"wait":"False"
},
{
"object":"GAMA_J093646.14+021914.23_N708",
"comment":"--",
"filter":"N708",
"seqtot":6,
"seqnum":3,
"seqid":"S2021A",
"expType":"object",
"proposer":"Leauthaud",
"program":"Merian",
"RA":144.1922647298,
"propid":"2020B-0288",
"dec":2.3206202133,
"expTime":600.0,
"count":1,
"wait":"False"
},
{
"object":"GAMA_J093757.02+021636.03_N708",
"comment":"--",
"filter":"N708",
"seqtot":6,
"seqnum":4,
"seqid":"S2021A",
"expType":"object",
"proposer":"Leauthaud",
"program":"Merian",
"RA":144.4875940097,
"propid":"2020B-0288",
"dec":2.2766761762,
"expTime":600.0,
"count":1,
"wait":"False"
},
{
"object":"GAMA_J093907.89+021356.84_N708",
"comment":"--",
"filter":"N708",
"seqtot":6,
"seqnum":5,
"seqid":"S2021A",
"expType":"object",
"proposer":"Leauthaud",
"program":"Merian",
"RA":144.7828821357,
"propid":"2020B-0288",
"dec":2.2324576675,
"expTime":600.0,
"count":1,
"wait":"False"
},
{
"object":"GAMA_J094859.44+003537.97_N708",
"comment":"--",
"filter":"N708",
"seqtot":6,
"seqnum":6,
"seqid":"S2021A",
"expType":"object",
"proposer":"Leauthaud",
"program":"Merian",
"RA":147.2476987752,
"propid":"2020B-0288",
"dec":0.5938820408,
"expTime":600.0,
"count":1,
"wait":"False"
}
]